package_name/__init__.py
package_name/file1_saudacao.py
package_name/file2_conta.py
desafio_dio_erisksnt-0.0.1.dist-info/METADATA
desafio_dio_erisksnt-0.0.1.dist-info/WHEEL
desafio_dio_erisksnt-0.0.1.dist-info/top_level.txt
desafio_dio_erisksnt-0.0.1.dist-info/RECORD
