Metadata-Version: 2.4
Name: desafio-dio-erisksnt
Version: 0.0.1
Summary: Aplicando os conhecimentos obtidos através da aula de criação de packages da DIO
Home-page: https://github.com/Erisksnt/simple-package-template
Author: Erick Santos
Author-email: santos.erisk@gmail.com
Requires-Python: >=3.6
Dynamic: author
Dynamic: author-email
Dynamic: description
Dynamic: description-content-type
Dynamic: home-page
Dynamic: requires-python
Dynamic: summary
